{
   "modifyDate": 1414708044000,
   "champions": [
      {
         "id": 53,
         "stats": {
            "totalDeathsPerSession": 5,
            "totalSessionsPlayed": 1,
            "totalDamageTaken": 21200,
            "totalQuadraKills": 0,
            "totalTripleKills": 0,
            "totalMinionKills": 33,
            "maxChampionsKilled": 3,
            "totalDoubleKills": 0,
            "totalPhysicalDamageDealt": 11285,
            "totalChampionKills": 3,
            "totalAssists": 12,
            "mostChampionKillsPerSession": 3,
            "totalDamageDealt": 23324,
            "totalFirstBlood": 0,
            "totalSessionsLost": 0,
            "totalSessionsWon": 1,
            "totalMagicDamageDealt": 8373,
            "totalGoldEarned": 10533,
            "totalPentaKills": 0,
            "totalTurretsKilled": 0,
            "mostSpellsCast": 0,
            "maxNumDeaths": 5,
            "totalUnrealKills": 0
         }
      },
      {
         "id": 68,
         "stats": {
            "totalDeathsPerSession": 74,
            "totalSessionsPlayed": 9,
            "totalDamageTaken": 209101,
            "totalQuadraKills": 0,
            "totalTripleKills": 3,
            "totalMinionKills": 1131,
            "maxChampionsKilled": 16,
            "totalDoubleKills": 11,
            "totalPhysicalDamageDealt": 130805,
            "totalChampionKills": 73,
            "totalAssists": 98,
            "mostChampionKillsPerSession": 16,
            "totalDamageDealt": 810400,
            "totalFirstBlood": 0,
            "totalSessionsLost": 5,
            "totalSessionsWon": 4,
            "totalMagicDamageDealt": 670603,
            "totalGoldEarned": 101264,
            "totalPentaKills": 0,
            "totalTurretsKilled": 8,
            "mostSpellsCast": 0,
            "maxNumDeaths": 13,
            "totalUnrealKills": 0
         }
      },
      {
         "id": 0,
         "stats": {
            "totalDamageTaken": 230301,
            "totalTripleKills": 3,
            "totalMinionKills": 1164,
            "maxChampionsKilled": 16,
            "maxLargestCriticalStrike": 0,
            "totalChampionKills": 76,
            "totalPhysicalDamageDealt": 142090,
            "rankedPremadeGamesPlayed": 0,
            "totalSessionsLost": 5,
            "totalNeutralMinionsKilled": 11,
            "totalSessionsWon": 5,
            "totalMagicDamageDealt": 678976,
            "maxLargestKillingSpree": 7,
            "totalPentaKills": 0,
            "maxTimeSpentLiving": 742,
            "totalDeathsPerSession": 79,
            "totalQuadraKills": 0,
            "totalSessionsPlayed": 10,
            "totalDoubleKills": 11,
            "totalAssists": 110,
            "maxTimePlayed": 2234,
            "mostChampionKillsPerSession": 16,
            "totalDamageDealt": 833724,
            "botGamesPlayed": 0,
            "killingSpree": 34,
            "totalFirstBlood": 0,
            "rankedSoloGamesPlayed": 0,
            "totalHeal": 12412,
            "totalGoldEarned": 111797,
            "mostSpellsCast": 0,
            "totalTurretsKilled": 8,
            "maxNumDeaths": 13,
            "totalUnrealKills": 0,
            "normalGamesPlayed": 0
         }
      }
   ],
   "summonerId": 43518871
}